nexium_exchanger_bot/__init__.py
nexium_exchanger_bot/api_client.py
nexium_exchanger_bot/api_response.py
nexium_exchanger_bot/configuration.py
nexium_exchanger_bot/exceptions.py
nexium_exchanger_bot/py.typed
nexium_exchanger_bot/rest.py
nexium_exchanger_bot/api/__init__.py
nexium_exchanger_bot/api/default_api.py
nexium_exchanger_bot/api/token_api.py
nexium_exchanger_bot/api/webhook_api.py
nexium_exchanger_bot/models/__init__.py
nexium_exchanger_bot/models/auth_entity_short_out.py
nexium_exchanger_bot/models/currency_out.py
nexium_exchanger_bot/models/customer_base_out_output.py
nexium_exchanger_bot/models/customer_coupon_out.py
nexium_exchanger_bot/models/customer_coupon_type_enum.py
nexium_exchanger_bot/models/customer_telegram_out.py
nexium_exchanger_bot/models/customer_token_request.py
nexium_exchanger_bot/models/customer_token_response.py
nexium_exchanger_bot/models/data.py
nexium_exchanger_bot/models/employee_short_out.py
nexium_exchanger_bot/models/employee_status_enum.py
nexium_exchanger_bot/models/exchanger_lookup_out.py
nexium_exchanger_bot/models/http_validation_error.py
nexium_exchanger_bot/models/incoming_payment_request_out_output.py
nexium_exchanger_bot/models/order_out_output.py
nexium_exchanger_bot/models/order_status_enum.py
nexium_exchanger_bot/models/order_type_enum.py
nexium_exchanger_bot/models/outgoing_payment_request_employee_data_out_output.py
nexium_exchanger_bot/models/outgoing_payment_request_out_output.py
nexium_exchanger_bot/models/payment_attachment_out.py
nexium_exchanger_bot/models/payment_customer_snapshot.py
nexium_exchanger_bot/models/payment_data_out.py
nexium_exchanger_bot/models/payment_employee_snapshot.py
nexium_exchanger_bot/models/payment_incoming_request_snapshot.py
nexium_exchanger_bot/models/payment_method_out.py
nexium_exchanger_bot/models/payment_out_output.py
nexium_exchanger_bot/models/payment_outgoing_request_snapshot.py
nexium_exchanger_bot/models/payment_payer_type_enum.py
nexium_exchanger_bot-0.1.4.dist-info/METADATA
nexium_exchanger_bot-0.1.4.dist-info/WHEEL
nexium_exchanger_bot-0.1.4.dist-info/top_level.txt
nexium_exchanger_bot-0.1.4.dist-info/RECORD
